{"edges":[[0,109],[1,109],[2,109],[3,109],[4,109],[5,109],[6,109],[7,109],[8,110],[9,110],[8,111],[9,111],[8,112],[9,112],[8,113],[9,113],[8,114],[9,114],[8,115],[9,115],[8,116],[9,116],[10,117],[11,117],[10,118],[11,118],[10,119],[11,119],[10,120],[11,120],[10,121],[11,121],[10,122],[11,122],[10,123],[11,123],[10,124],[11,124],[12,125],[13,125],[14,125],[15,125],[16,125],[17,125],[18,126],[18,127],[19,127],[18,128],[19,128],[18,129],[19,129],[18,130],[19,130],[18,131],[19,131],[18,132],[19,132],[18,133],[19,133],[18,134],[19,134],[18,117],[19,117],[18,118],[19,118],[18,119],[19,119],[18,120],[19,120],[18,121],[19,121],[18,122],[19,122],[18,123],[19,123],[20,124],[21,124],[20,117],[21,117],[20,118],[21,118],[20,119],[21,119],[20,120],[21,120],[20,121],[21,121],[20,122],[21,122],[20,123],[21,123],[22,135],[22,136],[22,137],[22,138],[22,139],[22,140],[22,141],[23,142],[24,142],[23,143],[24,143],[25,144],[26,144],[27,144],[28,144],[29,144],[25,145],[26,145],[27,145],[28,145],[29,145],[29,26],[26,29],[29,29],[30,146],[31,146],[30,147],[31,147],[30,148],[31,148],[30,149],[31,149],[30,150],[31,150],[32,30],[33,30],[34,30],[32,31],[33,31],[34,31],[35,151],[36,151],[37,151],[38,151],[39,151],[40,151],[41,151],[35,152],[36,152],[37,152],[38,152],[39,152],[40,152],[41,152],[35,153],[36,153],[37,153],[38,153],[39,153],[40,153],[41,153],[42,151],[43,151],[44,151],[45,151],[46,151],[47,151],[48,151],[42,152],[43,152],[44,152],[45,152],[46,152],[47,152],[48,152],[42,153],[43,153],[44,153],[45,153],[46,153],[47,153],[48,153],[49,151],[50,151],[51,151],[52,151],[53,151],[54,151],[55,151],[49,152],[50,152],[51,152],[52,152],[53,152],[54,152],[55,152],[49,153],[50,153],[51,153],[52,153],[53,153],[54,153],[55,153],[56,151],[57,151],[58,151],[59,151],[60,151],[61,151],[62,151],[56,152],[57,152],[58,152],[59,152],[60,152],[61,152],[62,152],[56,153],[57,153],[58,153],[59,153],[60,153],[61,153],[62,153],[63,151],[64,151],[65,151],[63,152],[64,152],[65,152],[63,153],[64,153],[65,153],[63,154],[64,154],[65,154],[63,155],[64,155],[65,155],[63,156],[64,156],[65,156],[63,157],[64,157],[65,157],[56,154],[57,154],[58,154],[59,154],[60,154],[61,154],[62,154],[56,155],[57,155],[58,155],[59,155],[60,155],[61,155],[62,155],[66,158],[67,158],[68,158],[69,158],[70,158],[71,158],[72,158],[73,158],[74,158],[75,158],[76,158],[77,158],[78,158],[79,158],[80,158],[81,158],[82,158],[83,158],[84,158],[85,158],[86,158],[87,158],[88,158],[89,158],[90,158],[91,158],[92,158],[93,158],[94,158],[95,158],[96,158],[97,158],[98,158],[99,158],[100,158],[101,158],[102,158],[103,158],[104,158],[105,158],[106,158],[107,158],[108,149],[108,150]],"features":{"0":"CCL5(CD4)","1":"CCL5(CD8)","2":"CCL5(Gran)","3":"CCL5(NK)","4":"CCL5(Tregs)","5":"CCL3(Gran)","6":"CCL3(Mo)","7":"CCL13(Mo)","8":"TNF(Gran)","9":"TNF(Mo)","10":"SPP1(Gran)","11":"SPP1(Mo)","12":"ANXA1(CD4)","13":"ANXA1(CD8)","14":"ANXA1(Gran)","15":"ANXA1(Mo)","16":"ANXA1(NK)","17":"ANXA1(Tregs)","18":"LGALS9(Gran)","19":"LGALS9(Mo)","20":"FN1(Gran)","21":"FN1(Mo)","22":"APP(Mo)","23":"CD86(Gran)","24":"CD86(Mo)","25":"CD99(CD4)","26":"CD99(CD8)","27":"CD99(Gran)","28":"CD99(Mo)","29":"CD99(NK)","30":"ICAM1(Gran)","31":"ICAM1(Mo)","32":"ITGB2(Gran)","33":"ITGB2(Mo)","34":"ITGB2(NK)","35":"HLA-A(B)","36":"HLA-A(CD4)","37":"HLA-A(CD8)","38":"HLA-A(Gran)","39":"HLA-A(Mo)","40":"HLA-A(NK)","41":"HLA-A(Tregs)","42":"HLA-B(B)","43":"HLA-B(CD4)","44":"HLA-B(CD8)","45":"HLA-B(Gran)","46":"HLA-B(Mo)","47":"HLA-B(NK)","48":"HLA-B(Tregs)","49":"HLA-C(B)","50":"HLA-C(CD4)","51":"HLA-C(CD8)","52":"HLA-C(Gran)","53":"HLA-C(Mo)","54":"HLA-C(NK)","55":"HLA-C(Tregs)","56":"HLA-F(B)","57":"HLA-F(CD4)","58":"HLA-F(CD8)","59":"HLA-F(Gran)","60":"HLA-F(Mo)","61":"HLA-F(NK)","62":"HLA-F(Tregs)","63":"HLA-G(CD4)","64":"HLA-G(Gran)","65":"HLA-G(NK)","66":"HLA-DPA1(B)","67":"HLA-DPA1(CD4)","68":"HLA-DPA1(CD8)","69":"HLA-DPA1(Gran)","70":"HLA-DPA1(Mo)","71":"HLA-DPA1(NK)","72":"HLA-DPA1(Tregs)","73":"HLA-DPB1(B)","74":"HLA-DPB1(CD4)","75":"HLA-DPB1(CD8)","76":"HLA-DPB1(Gran)","77":"HLA-DPB1(Mo)","78":"HLA-DPB1(NK)","79":"HLA-DPB1(Tregs)","80":"HLA-DQA1(B)","81":"HLA-DQA1(Gran)","82":"HLA-DQA1(Mo)","83":"HLA-DQA1(NK)","84":"HLA-DMA(B)","85":"HLA-DMA(Gran)","86":"HLA-DMA(Mo)","87":"HLA-DMB(Gran)","88":"HLA-DMB(Mo)","89":"HLA-DOA(Mo)","90":"HLA-DQB1(Gran)","91":"HLA-DQB1(Mo)","92":"HLA-DRA(B)","93":"HLA-DRA(CD4)","94":"HLA-DRA(Gran)","95":"HLA-DRA(Mo)","96":"HLA-DRA(NK)","97":"HLA-DRB1(B)","98":"HLA-DRB1(CD4)","99":"HLA-DRB1(CD8)","100":"HLA-DRB1(Gran)","101":"HLA-DRB1(Mo)","102":"HLA-DRB1(NK)","103":"HLA-DRB1(Tregs)","104":"HLA-DRB5(B)","105":"HLA-DRB5(Gran)","106":"HLA-DRB5(Mo)","107":"HLA-DRB5(NK)","108":"SIGLEC1(Mo)","109":"CCR1(Mo)","110":"TNFRSF1A(Gran)","111":"TNFRSF1A(Mo)","112":"TNFRSF1B(CD4)","113":"TNFRSF1B(CD8)","114":"TNFRSF1B(Gran)","115":"TNFRSF1B(Mo)","116":"TNFRSF1B(NK)","117":"CD44(B)","118":"CD44(CD4)","119":"CD44(CD8)","120":"CD44(Gran)","121":"CD44(Mo)","122":"CD44(NK)","123":"CD44(Tregs)","124":"ITGA4_ITGB1(NK)","125":"FPR1(Gran)","126":"PTPRC(B)","127":"PTPRC(CD4)","128":"PTPRC(CD8)","129":"PTPRC(Gran)","130":"PTPRC(Mo)","131":"PTPRC(NK)","132":"PTPRC(Tregs)","133":"HAVCR2(Gran)","134":"HAVCR2(Mo)","135":"CD74(B)","136":"CD74(CD4)","137":"CD74(CD8)","138":"CD74(Gran)","139":"CD74(Mo)","140":"CD74(NK)","141":"CD74(Tregs)","142":"CTLA4(NK)","143":"CTLA4(Tregs)","144":"PILRA(Gran)","145":"PILRA(Mo)","146":"ITGAX_ITGB2(Gran)","147":"ITGAX_ITGB2(Mo)","148":"ITGAM_ITGB2(Mo)","149":"SPN(CD8)","150":"SPN(NK)","151":"CD8A(CD8)","152":"CD8A(NK)","153":"CD8A(Tregs)","154":"LILRB1(Gran)","155":"LILRB1(Mo)","156":"LILRB2(Gran)","157":"LILRB2(Mo)","158":"CD4(Mo)"}}
